{
    "config": {
        "data": {
            "path": "data/epsilon"
        },
        "fit": {
            "logging_level": "Verbose"
        },
        "model": {
            "bagging_temperature": 0.647179179615835,
            "depth": 6,
            "early_stopping_rounds": 50,
            "iterations": 2000,
            "l2_leaf_reg": 3.445187999349453,
            "leaf_estimation_iterations": 9,
            "learning_rate": 0.1270822589383504,
            "metric_period": 10,
            "od_pval": 0.001,
            "task_type": "CPU",
            "thread_count": 10
        },
        "seed": 2
    },
    "environment": {
        "devices": {
            "CUDA_VISIBLE_DEVICES": "1",
            "torch.version.cuda": "10.1",
            "torch.backends.cudnn.version()": 7603,
            "torch.cuda.nccl.version()": 2708,
            "driver": "450.102.04",
            "1": {
                "name": "GeForce GTX 1080 Ti",
                "total_memory": 11721506816
            }
        }
    },
    "dataset": "epsilon",
    "algorithm": "catboost_",
    "metrics": {
        "train": {
            "0": {
                "precision": 0.9391340762917915,
                "recall": 0.938248554407963,
                "f1-score": 0.9386911065088572,
                "support": 160142
            },
            "1": {
                "precision": 0.9381972264060147,
                "recall": 0.9390834365499381,
                "f1-score": 0.9386401223008314,
                "support": 159858
            },
            "accuracy": 0.938665625,
            "macro avg": {
                "precision": 0.9386656513489031,
                "recall": 0.9386659954789505,
                "f1-score": 0.9386656144048443,
                "support": 320000
            },
            "weighted avg": {
                "precision": 0.9386660670760398,
                "recall": 0.938665625,
                "f1-score": 0.9386656370290866,
                "support": 320000
            },
            "roc_auc": 0.9386659954789505,
            "score": 0.9386659954789505
        },
        "val": {
            "0": {
                "precision": 0.8886389201349831,
                "recall": 0.8879730236043462,
                "f1-score": 0.8883058470764618,
                "support": 40035
            },
            "1": {
                "precision": 0.8878609826228279,
                "recall": 0.8885274615288378,
                "f1-score": 0.8881940970485244,
                "support": 39965
            },
            "accuracy": 0.88825,
            "macro avg": {
                "precision": 0.8882499513789055,
                "recall": 0.8882502425665919,
                "f1-score": 0.888249972062493,
                "support": 80000
            },
            "weighted avg": {
                "precision": 0.888250291726567,
                "recall": 0.88825,
                "f1-score": 0.8882500209531303,
                "support": 80000
            },
            "roc_auc": 0.8882502425665918,
            "score": 0.8882502425665918
        },
        "test": {
            "0": {
                "precision": 0.8857609301584773,
                "recall": 0.888999900089919,
                "f1-score": 0.8873774595354681,
                "support": 50045
            },
            "1": {
                "precision": 0.8883910632484128,
                "recall": 0.8851366229606646,
                "f1-score": 0.8867608571399922,
                "support": 49955
            },
            "accuracy": 0.88707,
            "macro avg": {
                "precision": 0.8870759967034451,
                "recall": 0.8870682615252918,
                "f1-score": 0.8870691583377301,
                "support": 100000
            },
            "weighted avg": {
                "precision": 0.8870748131435545,
                "recall": 0.88707,
                "f1-score": 0.8870694358088081,
                "support": 100000
            },
            "roc_auc": 0.8870682615252918,
            "score": 0.8870682615252918
        }
    }
}
