{
    "dataset": "data/covtype",
    "algorithm": "tabnet",
    "config": {
        "data": {
            "normalization": "quantile",
            "path": "data/covtype"
        },
        "model": {
            "batch_momentum": 0.95,
            "feature_dim": 64,
            "num_decision_steps": 4,
            "relaxation_factor": 1.94108401812561,
            "virtual_batch_size": 512
        },
        "seed": 5,
        "training": {
            "batch_size": 16384,
            "display_steps": 100,
            "epochs": 50000,
            "grad_thresh": 2000.0,
            "patience": 16,
            "schedule": {
                "decay_rate": 0.7334326000970233,
                "decay_steps": 500,
                "learning_rate": 0.007960556040014931
            },
            "sparsity_loss_weight": 0.0009207724255049557
        }
    },
    "environment": {
        "devices": {
            "CUDA_VISIBLE_DEVICES": "0",
            "torch.version.cuda": "10.2",
            "torch.backends.cudnn.version()": 7605,
            "torch.cuda.nccl.version()": 2708,
            "driver": "450.102.04",
            "0": {
                "name": "GeForce GTX 1080 Ti",
                "total_memory": 11720130560
            }
        }
    },
    "batch_size": 16384,
    "epoch_size": 22,
    "best_epoch": 226,
    "metrics": {
        "train": {
            "0": {
                "precision": 0.9763620341091701,
                "recall": 0.9724660343123516,
                "f1-score": 0.9744101398666002,
                "support": 135578
            },
            "1": {
                "precision": 0.9768198275909433,
                "recall": 0.9805749205788916,
                "f1-score": 0.978693772173918,
                "support": 181312
            },
            "2": {
                "precision": 0.9824998906243164,
                "recall": 0.9814264487369985,
                "f1-score": 0.9819628763199895,
                "support": 22882
            },
            "3": {
                "precision": 0.9607731665719159,
                "recall": 0.9607731665719159,
                "f1-score": 0.9607731665719159,
                "support": 1759
            },
            "4": {
                "precision": 0.9396195202646815,
                "recall": 0.9349794238683128,
                "f1-score": 0.9372937293729374,
                "support": 6075
            },
            "5": {
                "precision": 0.9625202229013122,
                "recall": 0.9634727845254161,
                "f1-score": 0.9629962681534104,
                "support": 11115
            },
            "6": {
                "precision": 0.9907791609036423,
                "recall": 0.9823251561785769,
                "f1-score": 0.9865340474368783,
                "support": 13126
            },
            "accuracy": 0.9763827595758471,
            "macro avg": {
                "precision": 0.9699105461379974,
                "recall": 0.968002562110352,
                "f1-score": 0.9689519999850927,
                "support": 371847
            },
            "weighted avg": {
                "precision": 0.9763841017059838,
                "recall": 0.9763827595758471,
                "f1-score": 0.9763794962237359,
                "support": 371847
            },
            "score": 0.9763827595758471
        },
        "val": {
            "0": {
                "precision": 0.93953170499792,
                "recall": 0.932878975629905,
                "f1-score": 0.936193521643868,
                "support": 33894
            },
            "1": {
                "precision": 0.9460273490744405,
                "recall": 0.9493249205788916,
                "f1-score": 0.9476732662364834,
                "support": 45328
            },
            "2": {
                "precision": 0.9367866549604916,
                "recall": 0.9325292780982346,
                "f1-score": 0.9346531184302733,
                "support": 5721
            },
            "3": {
                "precision": 0.813953488372093,
                "recall": 0.876993166287016,
                "f1-score": 0.8442982456140351,
                "support": 439
            },
            "4": {
                "precision": 0.8156887755102041,
                "recall": 0.8420013166556946,
                "f1-score": 0.8286362163913186,
                "support": 1519
            },
            "5": {
                "precision": 0.8752221827230715,
                "recall": 0.8859301907160849,
                "f1-score": 0.8805436337625178,
                "support": 2779
            },
            "6": {
                "precision": 0.9431714023831348,
                "recall": 0.9405850091407678,
                "f1-score": 0.9418764302059497,
                "support": 3282
            },
            "accuracy": 0.9379961704782599,
            "macro avg": {
                "precision": 0.8957687940030509,
                "recall": 0.9086061224437991,
                "f1-score": 0.9019820617549208,
                "support": 92962
            },
            "weighted avg": {
                "precision": 0.9381194419319606,
                "recall": 0.9379961704782599,
                "f1-score": 0.9380418027773622,
                "support": 92962
            },
            "score": 0.9379961704782599
        },
        "test": {
            "0": {
                "precision": 0.9403353759916393,
                "recall": 0.9344316465256798,
                "f1-score": 0.9373742156978809,
                "support": 42368
            },
            "1": {
                "precision": 0.9461585848807533,
                "recall": 0.9487301671343605,
                "f1-score": 0.947442631040925,
                "support": 56661
            },
            "2": {
                "precision": 0.9331569419300934,
                "recall": 0.937071738218431,
                "f1-score": 0.935110242813285,
                "support": 7151
            },
            "3": {
                "precision": 0.8020304568527918,
                "recall": 0.8633879781420765,
                "f1-score": 0.831578947368421,
                "support": 549
            },
            "4": {
                "precision": 0.8083116883116883,
                "recall": 0.8193786203264877,
                "f1-score": 0.8138075313807532,
                "support": 1899
            },
            "5": {
                "precision": 0.8730747290359384,
                "recall": 0.8813705729916499,
                "f1-score": 0.877203037684482,
                "support": 3473
            },
            "6": {
                "precision": 0.9441587068332109,
                "recall": 0.9397854705021941,
                "f1-score": 0.9419670128283445,
                "support": 4102
            },
            "accuracy": 0.9379534091202465,
            "macro avg": {
                "precision": 0.8924609262623022,
                "recall": 0.9034508848344114,
                "f1-score": 0.8977833741162987,
                "support": 116203
            },
            "weighted avg": {
                "precision": 0.9380467995316123,
                "recall": 0.9379534091202465,
                "f1-score": 0.9379888919834503,
                "support": 116203
            },
            "score": 0.9379534091202465
        }
    }
}
