{
    "config": {
        "data": {
            "path": "data/higgs_small"
        },
        "fit": {
            "logging_level": "Verbose"
        },
        "model": {
            "iterations": 2000,
            "task_type": "CPU",
            "thread_count": 10
        },
        "seed": 0
    },
    "environment": {
        "devices": {
            "CUDA_VISIBLE_DEVICES": "0",
            "torch.version.cuda": "10.1",
            "torch.backends.cudnn.version()": 7603,
            "torch.cuda.nccl.version()": 2708,
            "driver": "450.80.02",
            "0": {
                "name": "Tesla V100-PCIE-32GB",
                "total_memory": 34089730048
            }
        }
    },
    "dataset": "higgs_small",
    "algorithm": "catboost_",
    "metrics": {
        "train": {
            "0": {
                "precision": 0.823521210219945,
                "recall": 0.7986613481170982,
                "f1-score": 0.8109007911310943,
                "support": 29582
            },
            "1": {
                "precision": 0.8251475207703373,
                "recall": 0.8473620741634007,
                "f1-score": 0.8361072687519522,
                "support": 33170
            },
            "accuracy": 0.8244040030596634,
            "macro avg": {
                "precision": 0.8243343654951412,
                "recall": 0.8230117111402495,
                "f1-score": 0.8235040299415233,
                "support": 62752
            },
            "weighted avg": {
                "precision": 0.8243808596487522,
                "recall": 0.8244040030596634,
                "f1-score": 0.8242246511305182,
                "support": 62752
            },
            "roc_auc": 0.9073335331903285,
            "score": 0.8244040030596634
        },
        "val": {
            "0": {
                "precision": 0.7224847137298499,
                "recall": 0.702947539210384,
                "f1-score": 0.7125822368421052,
                "support": 7396
            },
            "1": {
                "precision": 0.7412859161563825,
                "recall": 0.7591654606849976,
                "f1-score": 0.7501191611058151,
                "support": 8292
            },
            "accuracy": 0.7326619071902091,
            "macro avg": {
                "precision": 0.7318853149431161,
                "recall": 0.7310564999476907,
                "f1-score": 0.7313506989739602,
                "support": 15688
            },
            "weighted avg": {
                "precision": 0.732422218225057,
                "recall": 0.7326619071902091,
                "f1-score": 0.7324226356179009,
                "support": 15688
            },
            "roc_auc": 0.8103567083757612,
            "score": 0.7326619071902091
        },
        "test": {
            "0": {
                "precision": 0.7146032451655924,
                "recall": 0.6955110870740941,
                "f1-score": 0.7049279175574193,
                "support": 9245
            },
            "1": {
                "precision": 0.7347342630983792,
                "recall": 0.7522431259044863,
                "f1-score": 0.7433856128140345,
                "support": 10365
            },
            "accuracy": 0.7254971953085161,
            "macro avg": {
                "precision": 0.7246687541319858,
                "recall": 0.7238771064892902,
                "f1-score": 0.7241567651857269,
                "support": 19610
            },
            "weighted avg": {
                "precision": 0.7252436327674963,
                "recall": 0.7254971953085161,
                "f1-score": 0.7252549961568491,
                "support": 19610
            },
            "roc_auc": 0.8036083180253886,
            "score": 0.7254971953085161
        }
    }
}
