{
    "dataset": "jannis",
    "algorithm": "node",
    "config": {
        "data": {
            "normalization": "quantile",
            "path": "data/jannis"
        },
        "model": {
            "bin_function": "entmoid15",
            "choice_function": "entmax15",
            "depth": 8,
            "layer_dim": 256,
            "num_layers": 8,
            "tree_dim": 4
        },
        "seed": 0,
        "training": {
            "batch_size": 512,
            "eval_batch_size": 8192,
            "lr": 0.001,
            "lr_n_decays": 0,
            "n_epochs": 1000000000,
            "optimizer": "adam",
            "patience": 16,
            "weight_decay": 0.0
        }
    },
    "environment": {
        "devices": {
            "CUDA_VISIBLE_DEVICES": "0",
            "torch.version.cuda": "10.1",
            "torch.backends.cudnn.version()": 7603,
            "torch.cuda.nccl.version()": 2708,
            "driver": "450.80.02",
            "0": {
                "name": "Tesla V100-PCIE-32GB",
                "total_memory": 34089730048
            }
        }
    },
    "batch_size": 512,
    "epoch_size": 105,
    "chunk_sizes": {},
    "eval_batch_sizes": {},
    "n_parameters": 61734912,
    "best_epoch_0": 13,
    "metrics_0": {
        "val": {
            "0": {
                "precision": 0.0,
                "recall": 0.0,
                "f1-score": 0.0,
                "support": 270
            },
            "1": {
                "precision": 0.45610612563402264,
                "recall": 0.5074886042978077,
                "f1-score": 0.48042741189766774,
                "support": 4607
            },
            "2": {
                "precision": 0.6903440621531631,
                "recall": 0.2638947815019092,
                "f1-score": 0.38182934315531,
                "support": 2357
            },
            "3": {
                "precision": 0.5825532492199159,
                "recall": 0.6966255678131084,
                "f1-score": 0.6345031400073883,
                "support": 6164
            },
            "accuracy": 0.541424093148231,
            "macro avg": {
                "precision": 0.4322508592517754,
                "recall": 0.36700223840320634,
                "f1-score": 0.3741899737650915,
                "support": 13398
            },
            "weighted avg": {
                "precision": 0.5462964698822592,
                "recall": 0.541424093148231,
                "f1-score": 0.5242855801936978,
                "support": 13398
            },
            "score": 0.541424093148231
        },
        "test": {
            "0": {
                "precision": 0.0,
                "recall": 0.0,
                "f1-score": 0.0,
                "support": 337
            },
            "1": {
                "precision": 0.36099969145325517,
                "recall": 0.40639110802361933,
                "f1-score": 0.3823529411764706,
                "support": 5758
            },
            "2": {
                "precision": 0.38461538461538464,
                "recall": 0.018663047166610113,
                "f1-score": 0.03559870550161813,
                "support": 2947
            },
            "3": {
                "precision": 0.46897846275439636,
                "recall": 0.6160934458144063,
                "f1-score": 0.5325629662870927,
                "support": 7705
            },
            "accuracy": 0.4264644413924882,
            "macro avg": {
                "precision": 0.30364838470575906,
                "recall": 0.2602869002511589,
                "f1-score": 0.23762865324129534,
                "support": 16747
            },
            "weighted avg": {
                "precision": 0.40757012105881685,
                "recall": 0.4264644413924882,
                "f1-score": 0.382748867000026,
                "support": 16747
            },
            "score": 0.4264644413924882
        }
    },
    "time_0": "0:29:54",
    "metrics": {
        "train": {
            "0": {
                "precision": 0.0,
                "recall": 0.0,
                "f1-score": 0.0,
                "support": 1080
            },
            "1": {
                "precision": 0.36997607071348343,
                "recall": 0.4111804613297151,
                "f1-score": 0.38949154285126725,
                "support": 18425
            },
            "2": {
                "precision": 0.6127049180327869,
                "recall": 0.06341463414634146,
                "f1-score": 0.11493369210071114,
                "support": 9430
            },
            "3": {
                "precision": 0.4849540998910845,
                "recall": 0.6321340202003813,
                "f1-score": 0.5488483482425864,
                "support": 24653
            },
            "accuracy": 0.44334552511756364,
            "macro avg": {
                "precision": 0.3669087721593387,
                "recall": 0.27668227891910946,
                "f1-score": 0.26331839579864125,
                "support": 53588
            },
            "weighted avg": {
                "precision": 0.4581284971366728,
                "recall": 0.44334552511756364,
                "f1-score": 0.40663888786237196,
                "support": 53588
            },
            "score": 0.44334552511756364
        },
        "val": {
            "0": {
                "precision": 0.0,
                "recall": 0.0,
                "f1-score": 0.0,
                "support": 270
            },
            "1": {
                "precision": 0.45610612563402264,
                "recall": 0.5074886042978077,
                "f1-score": 0.48042741189766774,
                "support": 4607
            },
            "2": {
                "precision": 0.6903440621531631,
                "recall": 0.2638947815019092,
                "f1-score": 0.38182934315531,
                "support": 2357
            },
            "3": {
                "precision": 0.5825532492199159,
                "recall": 0.6966255678131084,
                "f1-score": 0.6345031400073883,
                "support": 6164
            },
            "accuracy": 0.541424093148231,
            "macro avg": {
                "precision": 0.4322508592517754,
                "recall": 0.36700223840320634,
                "f1-score": 0.3741899737650915,
                "support": 13398
            },
            "weighted avg": {
                "precision": 0.5462964698822592,
                "recall": 0.541424093148231,
                "f1-score": 0.5242855801936978,
                "support": 13398
            },
            "score": 0.541424093148231
        },
        "test": {
            "0": {
                "precision": 0.0,
                "recall": 0.0,
                "f1-score": 0.0,
                "support": 337
            },
            "1": {
                "precision": 0.36099969145325517,
                "recall": 0.40639110802361933,
                "f1-score": 0.3823529411764706,
                "support": 5758
            },
            "2": {
                "precision": 0.38461538461538464,
                "recall": 0.018663047166610113,
                "f1-score": 0.03559870550161813,
                "support": 2947
            },
            "3": {
                "precision": 0.46897846275439636,
                "recall": 0.6160934458144063,
                "f1-score": 0.5325629662870927,
                "support": 7705
            },
            "accuracy": 0.4264644413924882,
            "macro avg": {
                "precision": 0.30364838470575906,
                "recall": 0.2602869002511589,
                "f1-score": 0.23762865324129534,
                "support": 16747
            },
            "weighted avg": {
                "precision": 0.40757012105881685,
                "recall": 0.4264644413924882,
                "f1-score": 0.382748867000026,
                "support": 16747
            },
            "score": 0.4264644413924882
        }
    },
    "time_final": "0:30:03"
}
