{
    "dataset": "epsilon",
    "algorithm": "resnet",
    "config": {
        "data": {
            "path": "data/epsilon"
        },
        "model": {
            "activation": "relu",
            "d": 345,
            "d_hidden_factor": 2.382820519109178,
            "hidden_dropout": 0.4699429446295502,
            "n_layers": 7,
            "normalization": "batchnorm",
            "residual_dropout": 0.3748513101145077
        },
        "seed": 12,
        "training": {
            "batch_size": 1024,
            "eval_batch_size": 8192,
            "lr": 1.176217687812856e-05,
            "n_epochs": 1000000000,
            "optimizer": "adamw",
            "patience": 16,
            "weight_decay": 0.0
        }
    },
    "environment": {
        "devices": {
            "CUDA_VISIBLE_DEVICES": "0",
            "torch.version.cuda": "10.1",
            "torch.backends.cudnn.version()": 7603,
            "torch.cuda.nccl.version()": 2708,
            "driver": "418.67",
            "0": {
                "name": "Tesla V100-PCIE-32GB",
                "total_memory": 34058272768
            }
        }
    },
    "epoch_size": 313,
    "n_parameters": 4674640,
    "best_epoch": 17,
    "metrics": {
        "train": {
            "0": {
                "precision": 0.9039275979716455,
                "recall": 0.9049718374942238,
                "f1-score": 0.9044494163241997,
                "support": 160142
            },
            "1": {
                "precision": 0.9046927157377891,
                "recall": 0.9036457355903365,
                "f1-score": 0.9041689225771521,
                "support": 159858
            },
            "accuracy": 0.904309375,
            "macro avg": {
                "precision": 0.9043101568547173,
                "recall": 0.9043087865422801,
                "f1-score": 0.904309169450676,
                "support": 320000
            },
            "weighted avg": {
                "precision": 0.9043098173337086,
                "recall": 0.904309375,
                "f1-score": 0.9043092939197762,
                "support": 320000
            },
            "roc_auc": 0.9043087865422801,
            "score": 0.9043087865422801
        },
        "val": {
            "0": {
                "precision": 0.8962798473015794,
                "recall": 0.8972648932184338,
                "f1-score": 0.8967720997578451,
                "support": 40035
            },
            "1": {
                "precision": 0.8969715187495303,
                "recall": 0.8959839859877393,
                "f1-score": 0.8964774804095836,
                "support": 39965
            },
            "accuracy": 0.896625,
            "macro avg": {
                "precision": 0.8966256830255548,
                "recall": 0.8966244396030866,
                "f1-score": 0.8966247900837143,
                "support": 80000
            },
            "weighted avg": {
                "precision": 0.8966253804192962,
                "recall": 0.896625,
                "f1-score": 0.8966249189796792,
                "support": 80000
            },
            "roc_auc": 0.8966244396030865,
            "score": 0.8966244396030865
        },
        "test": {
            "0": {
                "precision": 0.8950099403578529,
                "recall": 0.8995703866520132,
                "f1-score": 0.8972843689272011,
                "support": 50045
            },
            "1": {
                "precision": 0.8988732394366197,
                "recall": 0.8942848563707336,
                "f1-score": 0.8965731774622447,
                "support": 49955
            },
            "accuracy": 0.89693,
            "macro avg": {
                "precision": 0.8969415898972363,
                "recall": 0.8969276215113734,
                "f1-score": 0.8969287731947229,
                "support": 100000
            },
            "weighted avg": {
                "precision": 0.8969398514126509,
                "recall": 0.89693,
                "f1-score": 0.8969290932308821,
                "support": 100000
            },
            "roc_auc": 0.8969276215113735,
            "score": 0.8969276215113735
        }
    },
    "time": "0:04:29"
}
