{
    "dataset": "epsilon",
    "algorithm": "snn",
    "config": {
        "data": {
            "path": "data/epsilon"
        },
        "model": {
            "d_layers": [
                659,
                519
            ],
            "dropout": 0.02666417091576795
        },
        "seed": 14,
        "training": {
            "eval_batch_size": 8192,
            "lr": 0.0001101102378916963,
            "lr_n_decays": 0,
            "n_epochs": 1000000000,
            "optimizer": "adamw",
            "patience": 16,
            "weight_decay": 3.139165729748875e-05
        }
    },
    "environment": {
        "devices": {
            "CUDA_VISIBLE_DEVICES": "0",
            "torch.version.cuda": "10.1",
            "torch.backends.cudnn.version()": 7603,
            "torch.cuda.nccl.version()": 2708,
            "driver": "450.80.02",
            "0": {
                "name": "Tesla V100-PCIE-32GB",
                "total_memory": 34089730048
            }
        }
    },
    "batch_size": 1024,
    "epoch_size": 313,
    "n_parameters": 1661719,
    "best_epoch": 63,
    "metrics": {
        "train": {
            "0": {
                "precision": 0.899524775139022,
                "recall": 0.9030298110426996,
                "f1-score": 0.9012738853503185,
                "support": 160142
            },
            "1": {
                "precision": 0.9024768579574713,
                "recall": 0.898954071738668,
                "f1-score": 0.9007120203577651,
                "support": 159858
            },
            "accuracy": 0.90099375,
            "macro avg": {
                "precision": 0.9010008165482466,
                "recall": 0.9009919413906838,
                "f1-score": 0.9009929528540418,
                "support": 320000
            },
            "weighted avg": {
                "precision": 0.900999506561496,
                "recall": 0.90099375,
                "f1-score": 0.9009932021816323,
                "support": 320000
            },
            "roc_auc": 0.9646754133677747,
            "score": 0.90099375
        },
        "val": {
            "0": {
                "precision": 0.8952575064625174,
                "recall": 0.8996627950543274,
                "f1-score": 0.8974547447892659,
                "support": 40035
            },
            "1": {
                "precision": 0.8989891369945685,
                "recall": 0.8945577380207682,
                "f1-score": 0.8967679630767686,
                "support": 39965
            },
            "accuracy": 0.8971125,
            "macro avg": {
                "precision": 0.897123321728543,
                "recall": 0.8971102665375479,
                "f1-score": 0.8971113539330173,
                "support": 80000
            },
            "weighted avg": {
                "precision": 0.8971216891401851,
                "recall": 0.8971125,
                "f1-score": 0.8971116544000164,
                "support": 80000
            },
            "roc_auc": 0.9617523869666713,
            "score": 0.8971125
        },
        "test": {
            "0": {
                "precision": 0.8944863149543831,
                "recall": 0.9011889299630332,
                "f1-score": 0.8978251132235107,
                "support": 50045
            },
            "1": {
                "precision": 0.9002622025010085,
                "recall": 0.8935041537383646,
                "f1-score": 0.8968704475812529,
                "support": 49955
            },
            "accuracy": 0.89735,
            "macro avg": {
                "precision": 0.8973742587276958,
                "recall": 0.897346541850699,
                "f1-score": 0.8973477804023817,
                "support": 100000
            },
            "weighted avg": {
                "precision": 0.8973716595782998,
                "recall": 0.89735,
                "f1-score": 0.8973482100019208,
                "support": 100000
            },
            "roc_auc": 0.9617330426037647,
            "score": 0.89735
        }
    },
    "time": "0:03:03"
}
