{
    "dataset": "adult",
    "algorithm": "autoint",
    "config": {
        "data": {
            "cat_policy": "indices",
            "normalization": "quantile",
            "path": "data/adult"
        },
        "model": {
            "activation": "relu",
            "attention_dropout": 0.1017312794317322,
            "d_token": 32,
            "initialization": "kaiming",
            "n_heads": 2,
            "n_layers": 1,
            "prenormalization": false,
            "residual_dropout": 0.0
        },
        "seed": 2,
        "training": {
            "batch_size": 256,
            "eval_batch_size": 8192,
            "lr": 0.0001259942842444107,
            "n_epochs": 1000000000,
            "optimizer": "adamw",
            "patience": 16,
            "weight_decay": 3.937209095044005e-06
        }
    },
    "environment": {
        "devices": {
            "CUDA_VISIBLE_DEVICES": "0",
            "torch.version.cuda": "10.1",
            "torch.backends.cudnn.version()": 7603,
            "torch.cuda.nccl.version()": 2708,
            "driver": "450.80.02",
            "0": {
                "name": "Tesla V100-PCIE-32GB",
                "total_memory": 34089730048
            }
        }
    },
    "epoch_size": 102,
    "n_parameters": 8161,
    "best_epoch": 70,
    "metrics": {
        "train": {
            "0": {
                "precision": 0.8989963280293758,
                "recall": 0.9285461441213654,
                "f1-score": 0.9135323383084577,
                "support": 19775
            },
            "1": {
                "precision": 0.7487106526765072,
                "recall": 0.6711302407141718,
                "f1-score": 0.7078009414929387,
                "support": 6273
            },
            "accuracy": 0.8665540540540541,
            "macro avg": {
                "precision": 0.8238534903529415,
                "recall": 0.7998381924177687,
                "f1-score": 0.8106666399006982,
                "support": 26048
            },
            "weighted avg": {
                "precision": 0.8628038356503621,
                "recall": 0.8665540540540541,
                "f1-score": 0.8639871504927424,
                "support": 26048
            },
            "roc_auc": 0.924781780040601,
            "pr_auc": 0.812091807505504,
            "score": 0.8665540540540541
        },
        "val": {
            "0": {
                "precision": 0.892634450506625,
                "recall": 0.9263902932254803,
                "f1-score": 0.9091991664185769,
                "support": 4945
            },
            "1": {
                "precision": 0.7364228819695873,
                "recall": 0.6485969387755102,
                "f1-score": 0.6897253306205493,
                "support": 1568
            },
            "accuracy": 0.8595117457392907,
            "macro avg": {
                "precision": 0.8145286662381062,
                "recall": 0.7874936160004953,
                "f1-score": 0.799462248519563,
                "support": 6513
            },
            "weighted avg": {
                "precision": 0.8550266293080874,
                "recall": 0.8595117457392907,
                "f1-score": 0.8563610005147987,
                "support": 6513
            },
            "roc_auc": 0.9113214750005159,
            "pr_auc": 0.7821921733899371,
            "score": 0.8595117457392907
        },
        "test": {
            "0": {
                "precision": 0.8942255381984923,
                "recall": 0.9252915158825895,
                "f1-score": 0.9094933206861119,
                "support": 12435
            },
            "1": {
                "precision": 0.7278851786760399,
                "recall": 0.6461258450338013,
                "f1-score": 0.684573002754821,
                "support": 3846
            },
            "accuracy": 0.8593452490633253,
            "macro avg": {
                "precision": 0.8110553584372661,
                "recall": 0.7857086804581954,
                "f1-score": 0.7970331617204665,
                "support": 16281
            },
            "weighted avg": {
                "precision": 0.8549315745154659,
                "recall": 0.8593452490633253,
                "f1-score": 0.8563612315783332,
                "support": 16281
            },
            "roc_auc": 0.9126426842357169,
            "pr_auc": 0.7841637640856632,
            "score": 0.8593452490633253
        }
    },
    "time": "0:01:23"
}
