{
    "dataset": "covtype",
    "algorithm": "node",
    "config": {
        "data": {
            "normalization": "quantile",
            "path": "data/covtype"
        },
        "model": {
            "bin_function": "entmoid15",
            "choice_function": "entmax15",
            "depth": 8,
            "layer_dim": 512,
            "num_layers": 2,
            "tree_dim": 7
        },
        "seed": 12,
        "training": {
            "eval_batch_size": 512,
            "lr": 0.001,
            "lr_n_decays": 0,
            "n_epochs": 1000000000,
            "optimizer": "adam",
            "patience": 16,
            "weight_decay": 0.0
        }
    },
    "environment": {
        "devices": {
            "CUDA_VISIBLE_DEVICES": "0,1,2,3",
            "torch.version.cuda": "10.1",
            "torch.backends.cudnn.version()": 7603,
            "torch.cuda.nccl.version()": 2708,
            "driver": "450.80.02",
            "0": {
                "name": "Tesla V100-PCIE-32GB",
                "total_memory": 34089730048
            },
            "1": {
                "name": "Tesla V100-PCIE-32GB",
                "total_memory": 34089730048
            },
            "2": {
                "name": "Tesla V100-PCIE-32GB",
                "total_memory": 34089730048
            },
            "3": {
                "name": "Tesla V100-PCIE-32GB",
                "total_memory": 34089730048
            }
        }
    },
    "batch_size": 1024,
    "epoch_size": 364,
    "chunk_sizes": {},
    "eval_batch_sizes": {},
    "n_parameters": 16973824,
    "metrics": {
        "val": {
            "0": {
                "precision": 0.9584741241330251,
                "recall": 0.9540626659585767,
                "f1-score": 0.9562633073101492,
                "support": 33894
            },
            "1": {
                "precision": 0.9609814875670939,
                "recall": 0.9677020825979527,
                "f1-score": 0.9643300759566024,
                "support": 45328
            },
            "2": {
                "precision": 0.9516632016632016,
                "recall": 0.9601468274777137,
                "f1-score": 0.9558861915948837,
                "support": 5721
            },
            "3": {
                "precision": 0.8958333333333334,
                "recall": 0.8815489749430524,
                "f1-score": 0.8886337543053962,
                "support": 439
            },
            "4": {
                "precision": 0.9053295932678822,
                "recall": 0.8499012508229098,
                "f1-score": 0.8767402376910016,
                "support": 1519
            },
            "5": {
                "precision": 0.931185944363104,
                "recall": 0.9154372076286434,
                "f1-score": 0.9232444202504083,
                "support": 2779
            },
            "6": {
                "precision": 0.9686042897109108,
                "recall": 0.9494210847044485,
                "f1-score": 0.9589167564240653,
                "support": 3282
            },
            "accuracy": 0.9577246616897227,
            "macro avg": {
                "precision": 0.9388674248626503,
                "recall": 0.9254600134476139,
                "f1-score": 0.9320021062189295,
                "support": 92962
            },
            "weighted avg": {
                "precision": 0.9576552517399012,
                "recall": 0.9577246616897227,
                "f1-score": 0.9576612680525135,
                "support": 92962
            },
            "score": 0.9577246616897227
        },
        "test": {
            "0": {
                "precision": 0.9586007626175307,
                "recall": 0.9553200528700906,
                "f1-score": 0.9569575959617452,
                "support": 42368
            },
            "1": {
                "precision": 0.9603887575518781,
                "recall": 0.9679144385026738,
                "f1-score": 0.9641369126100944,
                "support": 56661
            },
            "2": {
                "precision": 0.9533815752852769,
                "recall": 0.958047825478954,
                "f1-score": 0.9557090046732231,
                "support": 7151
            },
            "3": {
                "precision": 0.885036496350365,
                "recall": 0.8834244080145719,
                "f1-score": 0.8842297174111211,
                "support": 549
            },
            "4": {
                "precision": 0.9116442363955529,
                "recall": 0.8204318062137967,
                "f1-score": 0.8636363636363638,
                "support": 1899
            },
            "5": {
                "precision": 0.926389292988071,
                "recall": 0.9167866397926865,
                "f1-score": 0.9215629522431259,
                "support": 3473
            },
            "6": {
                "precision": 0.9739674593241552,
                "recall": 0.9485616772306192,
                "f1-score": 0.9610967024824009,
                "support": 4102
            },
            "accuracy": 0.9576947238883677,
            "macro avg": {
                "precision": 0.9384869400732614,
                "recall": 0.9214981211576275,
                "f1-score": 0.9296184641454391,
                "support": 116203
            },
            "weighted avg": {
                "precision": 0.9576162243762921,
                "recall": 0.9576947238883677,
                "f1-score": 0.9576010128796447,
                "support": 116203
            },
            "score": 0.9576947238883677
        }
    },
    "time": "6:44:55"
}
