{
    "dataset": "higgs_small",
    "algorithm": "ft_transformer",
    "config": {
        "data": {
            "normalization": "quantile_normal",
            "path": "data/higgs_small"
        },
        "model": {
            "activation": "reglu",
            "attention_dropout": 0.2,
            "d_ffn_factor": 1.333333333333333,
            "d_token": 192,
            "ffn_dropout": 0.1,
            "initialization": "kaiming",
            "n_heads": 8,
            "n_layers": 3,
            "prenormalization": true,
            "residual_dropout": 0.0
        },
        "seed": 8,
        "training": {
            "batch_size": 512,
            "eval_batch_size": 8192,
            "lr": 0.0001,
            "lr_n_decays": 0,
            "n_epochs": 1000000000,
            "optimizer": "adamw",
            "patience": 16,
            "weight_decay": 1e-05
        }
    },
    "environment": {
        "devices": {
            "CUDA_VISIBLE_DEVICES": "0",
            "torch.version.cuda": "10.1",
            "torch.backends.cudnn.version()": 7603,
            "torch.cuda.nccl.version()": 2708,
            "driver": "450.80.02",
            "0": {
                "name": "Tesla V100-PCIE-32GB",
                "total_memory": 34089730048
            }
        }
    },
    "epoch_size": 123,
    "n_parameters": 900859,
    "best_epoch": 23,
    "metrics": {
        "train": {
            "0": {
                "precision": 0.7622884770346495,
                "recall": 0.7355148401054695,
                "f1-score": 0.7486623655913979,
                "support": 29582
            },
            "1": {
                "precision": 0.7712882574761027,
                "recall": 0.7954476936991257,
                "f1-score": 0.7831817034981227,
                "support": 33170
            },
            "accuracy": 0.7671946710861806,
            "macro avg": {
                "precision": 0.7667883672553761,
                "recall": 0.7654812669022977,
                "f1-score": 0.7659220345447603,
                "support": 62752
            },
            "weighted avg": {
                "precision": 0.7670456595506331,
                "recall": 0.7671946710861806,
                "f1-score": 0.7669088985842277,
                "support": 62752
            },
            "roc_auc": 0.8533429685045663,
            "score": 0.7671946710861806
        },
        "val": {
            "0": {
                "precision": 0.7262609185686109,
                "recall": 0.6969983775013521,
                "f1-score": 0.7113288257209879,
                "support": 7396
            },
            "1": {
                "precision": 0.7391152502910361,
                "recall": 0.7656777616980222,
                "f1-score": 0.7521620661059116,
                "support": 8292
            },
            "accuracy": 0.7332993370729219,
            "macro avg": {
                "precision": 0.7326880844298235,
                "recall": 0.7313380695996872,
                "f1-score": 0.7317454459134498,
                "support": 15688
            },
            "weighted avg": {
                "precision": 0.7330551637650891,
                "recall": 0.7332993370729219,
                "f1-score": 0.7329115149912446,
                "support": 15688
            },
            "roc_auc": 0.8148592220224644,
            "score": 0.7332993370729219
        },
        "test": {
            "0": {
                "precision": 0.7181192919156613,
                "recall": 0.688912925905895,
                "f1-score": 0.703212984431931,
                "support": 9245
            },
            "1": {
                "precision": 0.7322409459082022,
                "recall": 0.758803666184274,
                "f1-score": 0.7452857007486022,
                "support": 10365
            },
            "accuracy": 0.7258541560428353,
            "macro avg": {
                "precision": 0.7251801189119318,
                "recall": 0.7238582960450846,
                "f1-score": 0.7242493425902666,
                "support": 19610
            },
            "weighted avg": {
                "precision": 0.7255833889902501,
                "recall": 0.7258541560428353,
                "f1-score": 0.7254508072071629,
                "support": 19610
            },
            "roc_auc": 0.8071758792186856,
            "score": 0.7258541560428353
        }
    },
    "time": "0:03:05"
}
