{
    "config": {
        "data": {
            "path": "data/higgs_small"
        },
        "fit": {
            "logging_level": "Verbose"
        },
        "model": {
            "bagging_temperature": 0.3101033968272067,
            "depth": 7,
            "early_stopping_rounds": 50,
            "iterations": 2000,
            "l2_leaf_reg": 4.873718984440448,
            "leaf_estimation_iterations": 6,
            "learning_rate": 0.04072503701173266,
            "metric_period": 10,
            "od_pval": 0.001,
            "task_type": "CPU",
            "thread_count": 10
        },
        "seed": 0
    },
    "environment": {
        "devices": {
            "CUDA_VISIBLE_DEVICES": "1",
            "torch.version.cuda": "10.1",
            "torch.backends.cudnn.version()": 7603,
            "torch.cuda.nccl.version()": 2708,
            "driver": "450.102.04",
            "1": {
                "name": "GeForce GTX 1080 Ti",
                "total_memory": 11721506816
            }
        }
    },
    "dataset": "higgs_small",
    "algorithm": "catboost_",
    "metrics": {
        "train": {
            "0": {
                "precision": 0.8597987675382098,
                "recall": 0.8348319924278277,
                "f1-score": 0.8471314638538718,
                "support": 29582
            },
            "1": {
                "precision": 0.8564165858532429,
                "recall": 0.8785951160687369,
                "f1-score": 0.8673640976800251,
                "support": 33170
            },
            "accuracy": 0.8579646863844977,
            "macro avg": {
                "precision": 0.8581076766957263,
                "recall": 0.8567135542482822,
                "f1-score": 0.8572477807669485,
                "support": 62752
            },
            "weighted avg": {
                "precision": 0.8580109844159132,
                "recall": 0.8579646863844977,
                "f1-score": 0.8578262060774424,
                "support": 62752
            },
            "roc_auc": 0.8567135542482823,
            "score": 0.8567135542482823
        },
        "val": {
            "0": {
                "precision": 0.7231857915915083,
                "recall": 0.7047052460789616,
                "f1-score": 0.7138259261795521,
                "support": 7396
            },
            "1": {
                "precision": 0.742483197736116,
                "recall": 0.7594066570188133,
                "f1-score": 0.7508495796816312,
                "support": 8292
            },
            "accuracy": 0.7336180520142784,
            "macro avg": {
                "precision": 0.7328344946638121,
                "recall": 0.7320559515488874,
                "f1-score": 0.7323377529305917,
                "support": 15688
            },
            "weighted avg": {
                "precision": 0.733385567965239,
                "recall": 0.7336180520142784,
                "f1-score": 0.7333950321738942,
                "support": 15688
            },
            "roc_auc": 0.7320559515488874,
            "score": 0.7320559515488874
        },
        "test": {
            "0": {
                "precision": 0.7128691053327457,
                "recall": 0.6998377501352082,
                "f1-score": 0.7062933246001856,
                "support": 9245
            },
            "1": {
                "precision": 0.7365673058667173,
                "recall": 0.7485769416304873,
                "f1-score": 0.7425235657208478,
                "support": 10365
            },
            "accuracy": 0.7255991840897501,
            "macro avg": {
                "precision": 0.7247182055997314,
                "recall": 0.7242073458828477,
                "f1-score": 0.7244084451605166,
                "support": 19610
            },
            "weighted avg": {
                "precision": 0.7253949517649035,
                "recall": 0.7255991840897501,
                "f1-score": 0.7254430670385162,
                "support": 19610
            },
            "roc_auc": 0.7242073458828477,
            "score": 0.7242073458828477
        }
    }
}
